<?xml version="1.0" encoding="utf-8"?>
<ImportDUA xmlns:xsd="http://www.w3.org/2001/XMLSchema" xmlns:xsi="http://www.w3.org/2001/XMLSchema-instance" xmlns="http://aduanas.gob.do/XSD/ImportClearance/ImportDUA.xsd">
<ImpDeclaration xmlns="">
<DeclarationDate>2000-01-01T12:00:00</DeclarationDate>
<ClearanceType>IC38-002</ClearanceType>
<AreaCode>10150</AreaCode>
<FormNo>39155</FormNo>
<BLNo>PRELIQUIDACION</BLNo>
<ManifestNo/>
<ConsigneeCode>RNCCONSIGNATARIO</ConsigneeCode>
<ConsigneeName>NOMBRECONSIGNATARIO</ConsigneeName>
<ConsigneeNationality>214</ConsigneeNationality>
<CargoControlNo>SN</CargoControlNo>
<CommercialInvoiceNo/>
<DestinationLocationCode/>
<EntryPort/>
<DepartureCountryCode/>
<TransportCompanyCode/>
<TransportNationality/>
<TransportMethod/>
<EntryPlanDate>2000-01-01T12:00:00</EntryPlanDate>
<EntryDate>2000-01-01T12:00:00</EntryDate>
<ImporterCode>RNCIMPORTADOR</ImporterCode>
<ImporterName>NOMBREIMPORTADOR</ImporterName>
<ImporterNationality>214</ImporterNationality>
<BrokerEmployeeCode/>
<BrokerCompanyCode/>
<DeclarantCode>RNCDECLARANTE</DeclarantCode>
<DeclarantName>NOMBRE DEL AGENTE ADUANAL</DeclarantName>
<DeclarantNationality>214</DeclarantNationality>
<RegimenCode>1</RegimenCode>
<AgreementCode/>
<TotalFOB>550.0000</TotalFOB>
<InsuranceValue>200</InsuranceValue>
<FreightValue>1500</FreightValue>
<OtherValue>0</OtherValue>
<TotalCIF>3200</TotalCIF>
<TotalWeight/>
<NetWeight/>
<Remark/>
<ImpDeclarationSupplier>
<ForeignSupplierName>NOMBREDELAPROVEEDORA</ForeignSupplierName>
<ForeignSupplierCode>CODIGOPROVEEDOR</ForeignSupplierCode>
<ForeignSupplierNationality>724</ForeignSupplierNationality>
</ImpDeclarationSupplier>
<ImpDeclarationProduct>
<HSCode>84229090</HSCode>
<ProductCode>1</ProductCode>
<ProductName>Packaging machine spare parts</ProductName>
<BrandCode/>
<BrandName>N/A</BrandName>
<ModelCode/>
<ModelName>N/A</ModelName>
<ProductStatusCode>IC04-001</ProductStatusCode>
<ProductYear/>
<FOBValue>150.0000</FOBValue>
<UnitCode>1</UnitCode>
<Qty>10.0000</Qty>
<QtyPresentation>0</QtyPresentation>
<Weight>120</Weight>
<ProductSpecification/>
<TempProductYN>true</TempProductYN>
<CertificateOrignYN>false</CertificateOrignYN>
<CertificateOriginNo/>
<OriginCountry>840</OriginCountry>
<OrganicYN>true</OrganicYN>
<GradeAlcohol>0.00</GradeAlcohol>
<CustomerSalesPrice>0.0000</CustomerSalesPrice>
<ProductSerialNo/>
<VehicleType/>
<VehicleChassis/>
<VehicleColor/>
<VehicleMotor/>
<VehicleCC>0</VehicleCC>
<ProductDescription>Packaging machine spare parts</ProductDescription>
</ImpDeclarationProduct>
<ImpDeclarationProduct>
<HSCode>39249019</HSCode>
<ProductCode>2</ProductCode>
<ProductName>Plastic household articles</ProductName>
<BrandCode/>
<BrandName>N/A</BrandName>
<ModelCode/>
<ModelName>N/A</ModelName>
<ProductStatusCode>IC04-001</ProductStatusCode>
<ProductYear/>
<FOBValue>200.0000</FOBValue>
<UnitCode>1</UnitCode>
<Qty>50.0000</Qty>
<QtyPresentation>0</QtyPresentation>
<Weight>120</Weight>
<ProductSpecification/>
<TempProductYN>true</TempProductYN>
<CertificateOrignYN>false</CertificateOrignYN>
<CertificateOriginNo/>
<OriginCountry>724</OriginCountry>
<OrganicYN>true</OrganicYN>
<GradeAlcohol>0.00</GradeAlcohol>
<CustomerSalesPrice>0.0000</CustomerSalesPrice>
<ProductSerialNo/>
<VehicleType/>
<VehicleChassis/>
<VehicleColor/>
<VehicleMotor/>
<VehicleCC>0</VehicleCC>
<ProductDescription>Plastic household articles</ProductDescription>
</ImpDeclarationProduct>
<ImpDeclarationProduct>
<HSCode>95059000</HSCode>
<ProductCode>3</ProductCode>
<ProductName>Party and celebration articles</ProductName>
<BrandCode/>
<BrandName>N/A</BrandName>
<ModelCode/>
<ModelName>N/A</ModelName>
<ProductStatusCode>IC04-001</ProductStatusCode>
<ProductYear/>
<FOBValue>200.0000</FOBValue>
<UnitCode>1</UnitCode>
<Qty>100.0000</Qty>
<QtyPresentation>0</QtyPresentation>
<Weight>80</Weight>
<ProductSpecification/>
<TempProductYN>true</TempProductYN>
<CertificateOrignYN>false</CertificateOrignYN>
<CertificateOriginNo/>
<OriginCountry>156</OriginCountry>
<OrganicYN>true</OrganicYN>
<GradeAlcohol>0.00</GradeAlcohol>
<CustomerSalesPrice>0.0000</CustomerSalesPrice>
<ProductSerialNo/>
<VehicleType/>
<VehicleChassis/>
<VehicleColor/>
<VehicleMotor/>
<VehicleCC>0</VehicleCC>
<ProductDescription>Party and celebration articles</ProductDescription>
</ImpDeclarationProduct>
</ImpDeclaration>
</ImportDUA>